epi_models/__init__.py
epi_models/deterministic_compartmental_model.py
epi_models/deterministic_compartmental_model_scenario.py
epi_models/model.py
epi_models/params.py
epi_models/config/__init__.py
epi_models/config/compartmental_model.py
epi_models/config/epidemic_params.py
epi_models/config/contact_matrices/Albania.csv
epi_models/config/contact_matrices/Algeria.csv
epi_models/config/contact_matrices/Andorra.csv
epi_models/config/contact_matrices/Antigua and Barbuda.csv
epi_models/config/contact_matrices/Argentina.csv
epi_models/config/contact_matrices/Armenia.csv
epi_models/config/contact_matrices/Australia.csv
epi_models/config/contact_matrices/Austria.csv
epi_models/config/contact_matrices/Azerbaijan.csv
epi_models/config/contact_matrices/Bahamas.csv
epi_models/config/contact_matrices/Bahrain.csv
epi_models/config/contact_matrices/Bangladesh.csv
epi_models/config/contact_matrices/Belarus.csv
epi_models/config/contact_matrices/Belgium.csv
epi_models/config/contact_matrices/Belize.csv
epi_models/config/contact_matrices/Benin.csv
epi_models/config/contact_matrices/Bhutan.csv
epi_models/config/contact_matrices/Bolivia.csv
epi_models/config/contact_matrices/Bosnia and Herzegovina.csv
epi_models/config/contact_matrices/Botswana.csv
epi_models/config/contact_matrices/Brazil.csv
epi_models/config/contact_matrices/Brunei Darussalam.csv
epi_models/config/contact_matrices/Bulgaria.csv
epi_models/config/contact_matrices/Burkina Faso.csv
epi_models/config/contact_matrices/Cabo Verde.csv
epi_models/config/contact_matrices/Cambodia.csv
epi_models/config/contact_matrices/Cameroon.csv
epi_models/config/contact_matrices/Canada.csv
epi_models/config/contact_matrices/Chile.csv
epi_models/config/contact_matrices/China.csv
epi_models/config/contact_matrices/Colombia.csv
epi_models/config/contact_matrices/Congo.csv
epi_models/config/contact_matrices/Costa Rica.csv
epi_models/config/contact_matrices/Croatia.csv
epi_models/config/contact_matrices/Cyprus.csv
simulator_epi_models-0.1.3.dist-info/METADATA
simulator_epi_models-0.1.3.dist-info/WHEEL
simulator_epi_models-0.1.3.dist-info/top_level.txt
simulator_epi_models-0.1.3.dist-info/RECORD
